<?xml version="1.0" encoding="UTF-8" standalone="yes"?>
<atlas outputFormat="AFTrack" name="Cyprus 18" version="1">
    <Layer name="Cyprus 18">
        <PolygonMap name="Cyprus 18 00" zoom="0" mapSource="MapQuest" minTileCoordinate="0/0" maxTileCoordinate="255/255">
            <polygon>
                <point>151/101</point>
                <point>151/101</point>
                <point>151/101</point>
                <point>151/101</point>
                <point>151/101</point>
                <point>151/101</point>
                <point>151/101</point>
                <point>151/101</point>
                <point>151/101</point>
                <point>151/101</point>
                <point>151/101</point>
                <point>151/101</point>
                <point>151/101</point>
                <point>151/101</point>
                <point>151/101</point>
                <point>151/101</point>
                <point>151/101</point>
                <point>151/101</point>
                <point>151/101</point>
                <point>152/101</point>
                <point>152/101</point>
                <point>152/101</point>
                <point>152/101</point>
                <point>152/101</point>
                <point>152/101</point>
                <point>152/101</point>
                <point>152/101</point>
                <point>152/101</point>
                <point>152/101</point>
                <point>152/101</point>
                <point>152/101</point>
                <point>151/101</point>
                <point>151/101</point>
                <point>151/101</point>
                <point>151/101</point>
                <point>151/101</point>
                <point>151/101</point>
                <point>151/101</point>
                <point>151/101</point>
                <point>151/101</point>
                <point>151/101</point>
                <point>151/101</point>
                <point>151/101</point>
                <point>151/101</point>
                <point>151/101</point>
                <point>151/101</point>
                <point>151/101</point>
                <point>151/101</point>
                <point>151/101</point>
                <point>150/101</point>
                <point>150/101</point>
                <point>151/101</point>
                <point>151/101</point>
                <point>151/101</point>
                <point>151/101</point>
                <point>151/101</point>
            </polygon>
        </PolygonMap>
        <PolygonMap name="Cyprus 18 01" zoom="1" mapSource="MapQuest" minTileCoordinate="256/0" maxTileCoordinate="511/255">
            <polygon>
                <point>302/202</point>
                <point>302/202</point>
                <point>302/202</point>
                <point>302/202</point>
                <point>302/202</point>
                <point>302/202</point>
                <point>303/202</point>
                <point>303/202</point>
                <point>303/202</point>
                <point>303/202</point>
                <point>303/202</point>
                <point>303/202</point>
                <point>303/202</point>
                <point>303/202</point>
                <point>303/202</point>
                <point>303/202</point>
                <point>303/202</point>
                <point>303/202</point>
                <point>303/202</point>
                <point>304/202</point>
                <point>304/202</point>
                <point>304/202</point>
                <point>304/202</point>
                <point>304/202</point>
                <point>304/202</point>
                <point>304/202</point>
                <point>304/202</point>
                <point>304/202</point>
                <point>304/202</point>
                <point>304/202</point>
                <point>304/202</point>
                <point>303/202</point>
                <point>303/203</point>
                <point>303/203</point>
                <point>303/203</point>
                <point>303/203</point>
                <point>303/203</point>
                <point>303/203</point>
                <point>302/203</point>
                <point>302/203</point>
                <point>302/203</point>
                <point>302/203</point>
                <point>302/203</point>
                <point>302/203</point>
                <point>302/203</point>
                <point>302/203</point>
                <point>302/203</point>
                <point>302/203</point>
                <point>302/203</point>
                <point>301/202</point>
                <point>301/202</point>
                <point>302/202</point>
                <point>302/202</point>
                <point>302/202</point>
                <point>302/202</point>
                <point>302/202</point>
            </polygon>
        </PolygonMap>
        <PolygonMap name="Cyprus 18 02" zoom="2" mapSource="MapQuest" minTileCoordinate="512/256" maxTileCoordinate="767/511">
            <polygon>
                <point>605/405</point>
                <point>605/405</point>
                <point>605/405</point>
                <point>605/405</point>
                <point>605/405</point>
                <point>605/405</point>
                <point>606/405</point>
                <point>606/405</point>
                <point>606/405</point>
                <point>606/405</point>
                <point>606/405</point>
                <point>607/405</point>
                <point>607/405</point>
                <point>607/405</point>
                <point>607/405</point>
                <point>607/405</point>
                <point>607/405</point>
                <point>607/405</point>
                <point>607/405</point>
                <point>608/405</point>
                <point>608/405</point>
                <point>608/405</point>
                <point>608/405</point>
                <point>608/405</point>
                <point>608/405</point>
                <point>608/405</point>
                <point>608/405</point>
                <point>608/405</point>
                <point>608/405</point>
                <point>608/405</point>
                <point>608/405</point>
                <point>607/405</point>
                <point>607/406</point>
                <point>607/406</point>
                <point>606/406</point>
                <point>606/406</point>
                <point>606/406</point>
                <point>606/406</point>
                <point>605/406</point>
                <point>605/406</point>
                <point>605/407</point>
                <point>605/407</point>
                <point>605/406</point>
                <point>605/406</point>
                <point>605/406</point>
                <point>604/406</point>
                <point>604/406</point>
                <point>604/406</point>
                <point>604/406</point>
                <point>603/405</point>
                <point>603/405</point>
                <point>604/405</point>
                <point>604/405</point>
                <point>604/405</point>
                <point>604/404</point>
                <point>605/405</point>
            </polygon>
        </PolygonMap>
        <PolygonMap name="Cyprus 18 03" zoom="3" mapSource="MapQuest" minTileCoordinate="1024/768" maxTileCoordinate="1279/1023">
            <polygon>
                <point>1210/810</point>
                <point>1210/810</point>
                <point>1210/810</point>
                <point>1210/810</point>
                <point>1211/810</point>
                <point>1211/810</point>
                <point>1212/810</point>
                <point>1212/810</point>
                <point>1213/810</point>
                <point>1213/810</point>
                <point>1213/810</point>
                <point>1214/810</point>
                <point>1214/810</point>
                <point>1214/811</point>
                <point>1214/811</point>
                <point>1214/810</point>
                <point>1215/811</point>
                <point>1215/811</point>
                <point>1215/810</point>
                <point>1216/810</point>
                <point>1216/810</point>
                <point>1216/810</point>
                <point>1216/810</point>
                <point>1216/810</point>
                <point>1217/810</point>
                <point>1217/810</point>
                <point>1217/810</point>
                <point>1217/811</point>
                <point>1217/811</point>
                <point>1216/811</point>
                <point>1216/811</point>
                <point>1215/811</point>
                <point>1214/812</point>
                <point>1214/812</point>
                <point>1213/813</point>
                <point>1212/813</point>
                <point>1212/813</point>
                <point>1212/813</point>
                <point>1211/813</point>
                <point>1211/813</point>
                <point>1211/814</point>
                <point>1211/814</point>
                <point>1211/813</point>
                <point>1210/813</point>
                <point>1210/813</point>
                <point>1209/813</point>
                <point>1208/813</point>
                <point>1208/813</point>
                <point>1208/812</point>
                <point>1207/811</point>
                <point>1207/810</point>
                <point>1208/810</point>
                <point>1208/810</point>
                <point>1209/810</point>
                <point>1209/809</point>
                <point>1210/810</point>
            </polygon>
        </PolygonMap>
        <PolygonMap name="Cyprus 18 04" zoom="4" mapSource="MapQuest" minTileCoordinate="2304/1536" maxTileCoordinate="2559/1791">
            <polygon>
                <point>2420/1620</point>
                <point>2420/1620</point>
                <point>2420/1620</point>
                <point>2421/1621</point>
                <point>2422/1621</point>
                <point>2423/1620</point>
                <point>2424/1620</point>
                <point>2425/1620</point>
                <point>2426/1620</point>
                <point>2427/1620</point>
                <point>2427/1620</point>
                <point>2428/1620</point>
                <point>2428/1621</point>
                <point>2428/1622</point>
                <point>2428/1622</point>
                <point>2429/1621</point>
                <point>2430/1622</point>
                <point>2431/1622</point>
                <point>2431/1621</point>
                <point>2432/1621</point>
                <point>2432/1621</point>
                <point>2432/1621</point>
                <point>2433/1621</point>
                <point>2433/1621</point>
                <point>2434/1621</point>
                <point>2434/1621</point>
                <point>2435/1621</point>
                <point>2435/1622</point>
                <point>2434/1622</point>
                <point>2432/1622</point>
                <point>2432/1622</point>
                <point>2431/1622</point>
                <point>2429/1625</point>
                <point>2428/1625</point>
                <point>2426/1626</point>
                <point>2425/1626</point>
                <point>2424/1626</point>
                <point>2424/1626</point>
                <point>2423/1627</point>
                <point>2423/1627</point>
                <point>2423/1628</point>
                <point>2422/1628</point>
                <point>2422/1627</point>
                <point>2421/1627</point>
                <point>2420/1627</point>
                <point>2419/1627</point>
                <point>2417/1626</point>
                <point>2417/1626</point>
                <point>2416/1625</point>
                <point>2415/1623</point>
                <point>2415/1621</point>
                <point>2416/1621</point>
                <point>2417/1621</point>
                <point>2418/1620</point>
                <point>2419/1619</point>
                <point>2420/1620</point>
            </polygon>
        </PolygonMap>
        <PolygonMap name="Cyprus 18 05" zoom="5" mapSource="MapQuest" minTileCoordinate="4608/3072" maxTileCoordinate="5119/3327">
            <polygon>
                <point>4840/3240</point>
                <point>4840/3240</point>
                <point>4841/3241</point>
                <point>4843/3242</point>
                <point>4845/3242</point>
                <point>4846/3241</point>
                <point>4848/3240</point>
                <point>4851/3240</point>
                <point>4852/3240</point>
                <point>4854/3240</point>
                <point>4855/3240</point>
                <point>4856/3240</point>
                <point>4857/3242</point>
                <point>4857/3244</point>
                <point>4857/3244</point>
                <point>4858/3243</point>
                <point>4860/3244</point>
                <point>4862/3244</point>
                <point>4863/3243</point>
                <point>4864/3243</point>
                <point>4864/3243</point>
                <point>4865/3242</point>
                <point>4866/3242</point>
                <point>4867/3242</point>
                <point>4869/3243</point>
                <point>4869/3242</point>
                <point>4870/3243</point>
                <point>4870/3245</point>
                <point>4868/3245</point>
                <point>4865/3245</point>
                <point>4864/3245</point>
                <point>4862/3245</point>
                <point>4858/3250</point>
                <point>4856/3251</point>
                <point>4853/3252</point>
                <point>4851/3253</point>
                <point>4849/3253</point>
                <point>4848/3253</point>
                <point>4847/3254</point>
                <point>4847/3255</point>
                <point>4847/3256</point>
                <point>4845/3256</point>
                <point>4844/3254</point>
                <point>4843/3254</point>
                <point>4841/3254</point>
                <point>4839/3254</point>
                <point>4835/3252</point>
                <point>4834/3252</point>
                <point>4833/3250</point>
                <point>4831/3246</point>
                <point>4831/3242</point>
                <point>4833/3243</point>
                <point>4835/3242</point>
                <point>4836/3240</point>
                <point>4838/3239</point>
                <point>4840/3240</point>
            </polygon>
        </PolygonMap>
        <PolygonMap name="Cyprus 18 06" zoom="6" mapSource="MapQuest" minTileCoordinate="9472/6400" maxTileCoordinate="9983/6655">
            <polygon>
                <point>9680/6480</point>
                <point>9681/6481</point>
                <point>9683/6482</point>
                <point>9687/6484</point>
                <point>9690/6484</point>
                <point>9693/6482</point>
                <point>9697/6481</point>
                <point>9702/6480</point>
                <point>9705/6480</point>
                <point>9708/6481</point>
                <point>9711/6480</point>
                <point>9712/6481</point>
                <point>9714/6484</point>
                <point>9714/6489</point>
                <point>9715/6489</point>
                <point>9717/6487</point>
                <point>9721/6488</point>
                <point>9724/6488</point>
                <point>9727/6487</point>
                <point>9728/6487</point>
                <point>9729/6486</point>
                <point>9731/6485</point>
                <point>9733/6484</point>
                <point>9734/6484</point>
                <point>9738/6486</point>
                <point>9739/6485</point>
                <point>9740/6486</point>
                <point>9741/6490</point>
                <point>9736/6491</point>
                <point>9731/6491</point>
                <point>9728/6491</point>
                <point>9725/6491</point>
                <point>9717/6500</point>
                <point>9712/6503</point>
                <point>9707/6505</point>
                <point>9702/6506</point>
                <point>9699/6506</point>
                <point>9696/6507</point>
                <point>9694/6509</point>
                <point>9694/6511</point>
                <point>9694/6513</point>
                <point>9691/6512</point>
                <point>9689/6509</point>
                <point>9687/6508</point>
                <point>9682/6509</point>
                <point>9679/6509</point>
                <point>9671/6505</point>
                <point>9668/6504</point>
                <point>9667/6501</point>
                <point>9662/6492</point>
                <point>9662/6485</point>
                <point>9666/6486</point>
                <point>9670/6484</point>
                <point>9673/6480</point>
                <point>9677/6479</point>
                <point>9680/6480</point>
            </polygon>
        </PolygonMap>
        <PolygonMap name="Cyprus 18 07" zoom="7" mapSource="MapQuest" minTileCoordinate="19200/12800" maxTileCoordinate="19711/13055">
            <polygon>
                <point>19361/12960</point>
                <point>19362/12962</point>
                <point>19367/12965</point>
                <point>19375/12969</point>
                <point>19380/12969</point>
                <point>19386/12965</point>
                <point>19395/12962</point>
                <point>19405/12960</point>
                <point>19410/12961</point>
                <point>19417/12962</point>
                <point>19422/12961</point>
                <point>19425/12963</point>
                <point>19429/12968</point>
                <point>19429/12979</point>
                <point>19431/12979</point>
                <point>19435/12974</point>
                <point>19443/12977</point>
                <point>19449/12977</point>
                <point>19454/12974</point>
                <point>19456/12974</point>
                <point>19459/12973</point>
                <point>19463/12971</point>
                <point>19466/12969</point>
                <point>19469/12969</point>
                <point>19476/12972</point>
                <point>19478/12971</point>
                <point>19480/12973</point>
                <point>19483/12980</point>
                <point>19473/12982</point>
                <point>19462/12982</point>
                <point>19456/12982</point>
                <point>19451/12982</point>
                <point>19434/13000</point>
                <point>19425/13007</point>
                <point>19415/13010</point>
                <point>19404/13012</point>
                <point>19398/13012</point>
                <point>19393/13015</point>
                <point>19389/13019</point>
                <point>19389/13023</point>
                <point>19388/13026</point>
                <point>19382/13025</point>
                <point>19379/13019</point>
                <point>19375/13017</point>
                <point>19364/13018</point>
                <point>19359/13018</point>
                <point>19343/13011</point>
                <point>19337/13009</point>
                <point>19334/13003</point>
                <point>19325/12984</point>
                <point>19324/12970</point>
                <point>19332/12973</point>
                <point>19340/12969</point>
                <point>19347/12961</point>
                <point>19355/12959</point>
                <point>19361/12960</point>
            </polygon>
        </PolygonMap>
        <PolygonMap name="Cyprus 18 08" zoom="8" mapSource="MapQuest" minTileCoordinate="38400/25856" maxTileCoordinate="39167/26111">
            <polygon>
                <point>38722/25920</point>
                <point>38724/25925</point>
                <point>38735/25931</point>
                <point>38751/25938</point>
                <point>38760/25938</point>
                <point>38773/25931</point>
                <point>38790/25925</point>
                <point>38810/25920</point>
                <point>38820/25923</point>
                <point>38835/25925</point>
                <point>38844/25923</point>
                <point>38851/25927</point>
                <point>38859/25936</point>
                <point>38859/25958</point>
                <point>38862/25958</point>
                <point>38871/25949</point>
                <point>38886/25954</point>
                <point>38899/25954</point>
                <point>38908/25949</point>
                <point>38913/25949</point>
                <point>38919/25947</point>
                <point>38926/25943</point>
                <point>38933/25938</point>
                <point>38939/25938</point>
                <point>38952/25945</point>
                <point>38957/25943</point>
                <point>38961/25947</point>
                <point>38966/25960</point>
                <point>38946/25965</point>
                <point>38924/25965</point>
                <point>38913/25965</point>
                <point>38902/25965</point>
                <point>38868/26000</point>
                <point>38850/26014</point>
                <point>38830/26020</point>
                <point>38808/26025</point>
                <point>38797/26025</point>
                <point>38786/26031</point>
                <point>38779/26038</point>
                <point>38779/26047</point>
                <point>38777/26053</point>
                <point>38764/26051</point>
                <point>38759/26038</point>
                <point>38751/26034</point>
                <point>38729/26036</point>
                <point>38719/26036</point>
                <point>38686/26023</point>
                <point>38675/26018</point>
                <point>38668/26007</point>
                <point>38651/25969</point>
                <point>38648/25940</point>
                <point>38664/25947</point>
                <point>38680/25938</point>
                <point>38695/25923</point>
                <point>38711/25918</point>
                <point>38722/25920</point>
            </polygon>
        </PolygonMap>
        <PolygonMap name="Cyprus 18 09" zoom="9" mapSource="MapQuest" minTileCoordinate="77056/51712" maxTileCoordinate="78079/52223">
            <polygon>
                <point>77445/51841</point>
                <point>77448/51850</point>
                <point>77470/51863</point>
                <point>77503/51877</point>
                <point>77521/51877</point>
                <point>77547/51863</point>
                <point>77580/51850</point>
                <point>77620/51841</point>
                <point>77641/51846</point>
                <point>77671/51850</point>
                <point>77689/51846</point>
                <point>77703/51855</point>
                <point>77718/51872</point>
                <point>77718/51917</point>
                <point>77725/51917</point>
                <point>77743/51899</point>
                <point>77773/51908</point>
                <point>77798/51908</point>
                <point>77816/51899</point>
                <point>77827/51899</point>
                <point>77838/51895</point>
                <point>77853/51886</point>
                <point>77867/51877</point>
                <point>77878/51877</point>
                <point>77904/51890</point>
                <point>77915/51886</point>
                <point>77922/51895</point>
                <point>77933/51921</point>
                <point>77893/51930</point>
                <point>77849/51930</point>
                <point>77827/51930</point>
                <point>77805/51930</point>
                <point>77736/52001</point>
                <point>77700/52028</point>
                <point>77660/52041</point>
                <point>77616/52050</point>
                <point>77594/52050</point>
                <point>77572/52063</point>
                <point>77558/52076</point>
                <point>77558/52094</point>
                <point>77554/52107</point>
                <point>77529/52103</point>
                <point>77518/52076</point>
                <point>77503/52068</point>
                <point>77459/52072</point>
                <point>77438/52072</point>
                <point>77372/52046</point>
                <point>77350/52037</point>
                <point>77336/52014</point>
                <point>77303/51939</point>
                <point>77296/51881</point>
                <point>77328/51895</point>
                <point>77361/51877</point>
                <point>77390/51846</point>
                <point>77423/51837</point>
                <point>77445/51841</point>
            </polygon>
        </PolygonMap>
        <PolygonMap name="Cyprus 18 10" zoom="10" mapSource="MapQuest" minTileCoordinate="154368/103424" maxTileCoordinate="155903/104447">
            <polygon>
                <point>154890/103683</point>
                <point>154897/103701</point>
                <point>154941/103727</point>
                <point>155007/103754</point>
                <point>155043/103754</point>
                <point>155094/103727</point>
                <point>155160/103701</point>
                <point>155240/103683</point>
                <point>155283/103692</point>
                <point>155342/103701</point>
                <point>155378/103692</point>
                <point>155407/103710</point>
                <point>155436/103745</point>
                <point>155436/103834</point>
                <point>155451/103834</point>
                <point>155487/103799</point>
                <point>155546/103816</point>
                <point>155597/103816</point>
                <point>155633/103799</point>
                <point>155655/103799</point>
                <point>155677/103790</point>
                <point>155706/103772</point>
                <point>155735/103754</point>
                <point>155757/103754</point>
                <point>155808/103781</point>
                <point>155830/103772</point>
                <point>155844/103790</point>
                <point>155866/103843</point>
                <point>155786/103861</point>
                <point>155698/103861</point>
                <point>155655/103861</point>
                <point>155611/103861</point>
                <point>155473/104003</point>
                <point>155400/104056</point>
                <point>155320/104083</point>
                <point>155232/104100</point>
                <point>155189/104100</point>
                <point>155145/104127</point>
                <point>155116/104153</point>
                <point>155116/104189</point>
                <point>155109/104215</point>
                <point>155058/104207</point>
                <point>155036/104153</point>
                <point>155007/104136</point>
                <point>154919/104145</point>
                <point>154876/104145</point>
                <point>154745/104092</point>
                <point>154701/104074</point>
                <point>154672/104029</point>
                <point>154606/103879</point>
                <point>154592/103763</point>
                <point>154657/103790</point>
                <point>154723/103754</point>
                <point>154781/103692</point>
                <point>154847/103674</point>
                <point>154890/103683</point>
            </polygon>
        </PolygonMap>
        <PolygonMap name="Cyprus 18 11" zoom="11" mapSource="MapQuest" minTileCoordinate="308992/207104" maxTileCoordinate="311807/208639">
            <polygon>
                <point>309781/207366</point>
                <point>309795/207402</point>
                <point>309883/207455</point>
                <point>310014/207509</point>
                <point>310087/207509</point>
                <point>310189/207455</point>
                <point>310320/207402</point>
                <point>310480/207366</point>
                <point>310567/207384</point>
                <point>310684/207402</point>
                <point>310757/207384</point>
                <point>310815/207420</point>
                <point>310873/207491</point>
                <point>310873/207669</point>
                <point>310902/207669</point>
                <point>310975/207598</point>
                <point>311092/207633</point>
                <point>311194/207633</point>
                <point>311266/207598</point>
                <point>311310/207598</point>
                <point>311354/207580</point>
                <point>311412/207544</point>
                <point>311470/207509</point>
                <point>311514/207509</point>
                <point>311616/207562</point>
                <point>311660/207544</point>
                <point>311689/207580</point>
                <point>311732/207687</point>
                <point>311572/207722</point>
                <point>311397/207722</point>
                <point>311310/207722</point>
                <point>311223/207722</point>
                <point>310946/208006</point>
                <point>310800/208113</point>
                <point>310640/208166</point>
                <point>310465/208201</point>
                <point>310378/208201</point>
                <point>310291/208254</point>
                <point>310232/208307</point>
                <point>310232/208378</point>
                <point>310218/208431</point>
                <point>310116/208414</point>
                <point>310072/208307</point>
                <point>310014/208272</point>
                <point>309839/208290</point>
                <point>309752/208290</point>
                <point>309490/208184</point>
                <point>309402/208148</point>
                <point>309344/208059</point>
                <point>309213/207758</point>
                <point>309184/207527</point>
                <point>309315/207580</point>
                <point>309446/207509</point>
                <point>309562/207384</point>
                <point>309694/207348</point>
                <point>309781/207366</point>
            </polygon>
        </PolygonMap>
        <PolygonMap name="Cyprus 18 12" zoom="12" mapSource="MapQuest" minTileCoordinate="618240/414464" maxTileCoordinate="623615/417023">
            <polygon>
                <point>619562/414733</point>
                <point>619591/414804</point>
                <point>619766/414911</point>
                <point>620028/415018</point>
                <point>620174/415018</point>
                <point>620378/414911</point>
                <point>620640/414804</point>
                <point>620960/414733</point>
                <point>621135/414769</point>
                <point>621368/414804</point>
                <point>621514/414769</point>
                <point>621630/414840</point>
                <point>621747/414982</point>
                <point>621747/415338</point>
                <point>621805/415338</point>
                <point>621951/415196</point>
                <point>622184/415267</point>
                <point>622388/415267</point>
                <point>622533/415196</point>
                <point>622621/415196</point>
                <point>622708/415160</point>
                <point>622825/415089</point>
                <point>622941/415018</point>
                <point>623028/415018</point>
                <point>623232/415125</point>
                <point>623320/415089</point>
                <point>623378/415160</point>
                <point>623465/415374</point>
                <point>623145/415445</point>
                <point>622795/415445</point>
                <point>622621/415445</point>
                <point>622446/415445</point>
                <point>621892/416013</point>
                <point>621601/416226</point>
                <point>621281/416332</point>
                <point>620931/416403</point>
                <point>620756/416403</point>
                <point>620582/416509</point>
                <point>620465/416615</point>
                <point>620465/416757</point>
                <point>620436/416863</point>
                <point>620232/416828</point>
                <point>620145/416615</point>
                <point>620028/416545</point>
                <point>619679/416580</point>
                <point>619504/416580</point>
                <point>618980/416368</point>
                <point>618805/416297</point>
                <point>618688/416119</point>
                <point>618426/415516</point>
                <point>618368/415054</point>
                <point>618630/415160</point>
                <point>618892/415018</point>
                <point>619125/414769</point>
                <point>619388/414697</point>
                <point>619562/414733</point>
            </polygon>
        </PolygonMap>
        <PolygonMap name="Cyprus 18 13" zoom="13" mapSource="MapQuest" minTileCoordinate="1236736/829184" maxTileCoordinate="1246975/833791">
            <polygon>
                <point>1239125/829467</point>
                <point>1239183/829609</point>
                <point>1239533/829823</point>
                <point>1240057/830036</point>
                <point>1240348/830036</point>
                <point>1240756/829823</point>
                <point>1241280/829609</point>
                <point>1241921/829467</point>
                <point>1242271/829538</point>
                <point>1242737/829609</point>
                <point>1243028/829538</point>
                <point>1243261/829680</point>
                <point>1243494/829965</point>
                <point>1243494/830677</point>
                <point>1243611/830677</point>
                <point>1243902/830392</point>
                <point>1244368/830535</point>
                <point>1244776/830535</point>
                <point>1245067/830392</point>
                <point>1245242/830392</point>
                <point>1245417/830321</point>
                <point>1245650/830179</point>
                <point>1245883/830036</point>
                <point>1246057/830036</point>
                <point>1246465/830250</point>
                <point>1246640/830179</point>
                <point>1246756/830321</point>
                <point>1246931/830748</point>
                <point>1246290/830890</point>
                <point>1245591/830890</point>
                <point>1245242/830890</point>
                <point>1244892/830890</point>
                <point>1243785/832026</point>
                <point>1243203/832452</point>
                <point>1242562/832665</point>
                <point>1241863/832806</point>
                <point>1241513/832806</point>
                <point>1241164/833019</point>
                <point>1240931/833231</point>
                <point>1240931/833515</point>
                <point>1240873/833727</point>
                <point>1240465/833656</point>
                <point>1240290/833231</point>
                <point>1240057/833090</point>
                <point>1239358/833161</point>
                <point>1239009/833161</point>
                <point>1237960/832736</point>
                <point>1237610/832594</point>
                <point>1237377/832239</point>
                <point>1236853/831032</point>
                <point>1236737/830108</point>
                <point>1237261/830321</point>
                <point>1237785/830036</point>
                <point>1238251/829538</point>
                <point>1238776/829395</point>
                <point>1239125/829467</point>
            </polygon>
        </PolygonMap>
        <PolygonMap name="Cyprus 18 14" zoom="14" mapSource="MapQuest" minTileCoordinate="2473472/1658624" maxTileCoordinate="2493951/1667583">
            <polygon>
                <point>2478251/1658934</point>
                <point>2478367/1659219</point>
                <point>2479066/1659646</point>
                <point>2480115/1660073</point>
                <point>2480697/1660073</point>
                <point>2481513/1659646</point>
                <point>2482561/1659219</point>
                <point>2483843/1658934</point>
                <point>2484542/1659076</point>
                <point>2485474/1659219</point>
                <point>2486057/1659076</point>
                <point>2486523/1659361</point>
                <point>2486989/1659931</point>
                <point>2486989/1661354</point>
                <point>2487222/1661354</point>
                <point>2487804/1660785</point>
                <point>2488736/1661070</point>
                <point>2489552/1661070</point>
                <point>2490134/1660785</point>
                <point>2490484/1660785</point>
                <point>2490834/1660643</point>
                <point>2491300/1660358</point>
                <point>2491766/1660073</point>
                <point>2492115/1660073</point>
                <point>2492931/1660501</point>
                <point>2493280/1660358</point>
                <point>2493513/1660643</point>
                <point>2493863/1661496</point>
                <point>2492581/1661781</point>
                <point>2491183/1661781</point>
                <point>2490484/1661781</point>
                <point>2489785/1661781</point>
                <point>2487571/1664053</point>
                <point>2486406/1664905</point>
                <point>2485125/1665330</point>
                <point>2483727/1665613</point>
                <point>2483027/1665613</point>
                <point>2482328/1666038</point>
                <point>2481862/1666463</point>
                <point>2481862/1667030</point>
                <point>2481746/1667454</point>
                <point>2480930/1667313</point>
                <point>2480581/1666463</point>
                <point>2480115/1666180</point>
                <point>2478717/1666322</point>
                <point>2478018/1666322</point>
                <point>2475920/1665472</point>
                <point>2475221/1665188</point>
                <point>2474755/1664479</point>
                <point>2473707/1662065</point>
                <point>2473474/1660216</point>
                <point>2474522/1660643</point>
                <point>2475571/1660073</point>
                <point>2476503/1659076</point>
                <point>2477552/1658791</point>
                <point>2478251/1658934</point>
            </polygon>
        </PolygonMap>
        <PolygonMap name="Cyprus 18 15" zoom="15" mapSource="MapQuest" minTileCoordinate="4946944/3317504" maxTileCoordinate="4987903/3334911">
            <polygon>
                <point>4956502/3317868</point>
                <point>4956735/3318438</point>
                <point>4958133/3319293</point>
                <point>4960230/3320147</point>
                <point>4961395/3320147</point>
                <point>4963026/3319293</point>
                <point>4965123/3318438</point>
                <point>4967687/3317868</point>
                <point>4969085/3318153</point>
                <point>4970949/3318438</point>
                <point>4972114/3318153</point>
                <point>4973046/3318723</point>
                <point>4973978/3319863</point>
                <point>4973978/3322709</point>
                <point>4974444/3322709</point>
                <point>4975609/3321571</point>
                <point>4977473/3322140</point>
                <point>4979104/3322140</point>
                <point>4980269/3321571</point>
                <point>4980969/3321571</point>
                <point>4981668/3321286</point>
                <point>4982600/3320717</point>
                <point>4983532/3320147</point>
                <point>4984231/3320147</point>
                <point>4985862/3321002</point>
                <point>4986561/3320717</point>
                <point>4987027/3321286</point>
                <point>4987726/3322993</point>
                <point>4985163/3323562</point>
                <point>4982367/3323562</point>
                <point>4980969/3323562</point>
                <point>4979570/3323562</point>
                <point>4975143/3328107</point>
                <point>4972813/3329810</point>
                <point>4970250/3330660</point>
                <point>4967454/3331227</point>
                <point>4966055/3331227</point>
                <point>4964657/3332077</point>
                <point>4963725/3332927</point>
                <point>4963725/3334060</point>
                <point>4963492/3334909</point>
                <point>4961861/3334626</point>
                <point>4961162/3332927</point>
                <point>4960230/3332361</point>
                <point>4957434/3332644</point>
                <point>4956036/3332644</point>
                <point>4951841/3330944</point>
                <point>4950443/3330377</point>
                <point>4949511/3328959</point>
                <point>4947414/3324131</point>
                <point>4946948/3320432</point>
                <point>4949045/3321286</point>
                <point>4951142/3320147</point>
                <point>4953006/3318153</point>
                <point>4955104/3317583</point>
                <point>4956502/3317868</point>
            </polygon>
        </PolygonMap>
        <PolygonMap name="Cyprus 18 16" zoom="16" mapSource="MapQuest" minTileCoordinate="9893888/6635008" maxTileCoordinate="9975551/6669823">
            <polygon>
                <point>9913004/6635737</point>
                <point>9913470/6636877</point>
                <point>9916266/6638586</point>
                <point>9920461/6640295</point>
                <point>9922791/6640295</point>
                <point>9926053/6638586</point>
                <point>9930247/6636877</point>
                <point>9935374/6635737</point>
                <point>9938170/6636307</point>
                <point>9941898/6636877</point>
                <point>9944228/6636307</point>
                <point>9946092/6637447</point>
                <point>9947957/6639726</point>
                <point>9947957/6645418</point>
                <point>9948889/6645418</point>
                <point>9951219/6643142</point>
                <point>9954947/6644280</point>
                <point>9958209/6644280</point>
                <point>9960539/6643142</point>
                <point>9961938/6643142</point>
                <point>9963336/6642573</point>
                <point>9965200/6641434</point>
                <point>9967064/6640295</point>
                <point>9968462/6640295</point>
                <point>9971724/6642004</point>
                <point>9973122/6641434</point>
                <point>9974054/6642573</point>
                <point>9975453/6645987</point>
                <point>9970326/6647125</point>
                <point>9964734/6647125</point>
                <point>9961938/6647125</point>
                <point>9959141/6647125</point>
                <point>9950287/6656215</point>
                <point>9945626/6659620</point>
                <point>9940500/6661321</point>
                <point>9934908/6662455</point>
                <point>9932111/6662455</point>
                <point>9929315/6664155</point>
                <point>9927451/6665855</point>
                <point>9927451/6668120</point>
                <point>9926985/6669818</point>
                <point>9923723/6669252</point>
                <point>9922325/6665855</point>
                <point>9920461/6664722</point>
                <point>9914868/6665288</point>
                <point>9912072/6665288</point>
                <point>9903683/6661888</point>
                <point>9900887/6660754</point>
                <point>9899023/6657918</point>
                <point>9894829/6648262</point>
                <point>9893897/6640865</point>
                <point>9898091/6642573</point>
                <point>9902285/6640295</point>
                <point>9906013/6636307</point>
                <point>9910208/6635166</point>
                <point>9913004/6635737</point>
            </polygon>
        </PolygonMap>
        <PolygonMap name="Cyprus 18 17" zoom="17" mapSource="MapQuest" minTileCoordinate="19787776/13270272" maxTileCoordinate="19951103/13339647">
            <polygon>
                <point>19826008/13271474</point>
                <point>19826941/13273754</point>
                <point>19832533/13277173</point>
                <point>19840922/13280591</point>
                <point>19845582/13280591</point>
                <point>19852106/13277173</point>
                <point>19860495/13273754</point>
                <point>19870748/13271474</point>
                <point>19876340/13272614</point>
                <point>19883797/13273754</point>
                <point>19888457/13272614</point>
                <point>19892185/13274894</point>
                <point>19895914/13279452</point>
                <point>19895914/13290837</point>
                <point>19897778/13290837</point>
                <point>19902438/13286285</point>
                <point>19909895/13288561</point>
                <point>19916419/13288561</point>
                <point>19921079/13286285</point>
                <point>19923876/13286285</point>
                <point>19926672/13285146</point>
                <point>19930400/13282869</point>
                <point>19934128/13280591</point>
                <point>19936925/13280591</point>
                <point>19943449/13284008</point>
                <point>19946245/13282869</point>
                <point>19948109/13285146</point>
                <point>19950906/13291975</point>
                <point>19940653/13294250</point>
                <point>19929468/13294250</point>
                <point>19923876/13294250</point>
                <point>19918283/13294250</point>
                <point>19900574/13312431</point>
                <point>19891253/13319240</point>
                <point>19881000/13322643</point>
                <point>19869816/13324910</point>
                <point>19864223/13324910</point>
                <point>19858631/13328311</point>
                <point>19854903/13331710</point>
                <point>19854903/13336241</point>
                <point>19853971/13339637</point>
                <point>19847446/13338505</point>
                <point>19844650/13331710</point>
                <point>19840922/13329444</point>
                <point>19829737/13330577</point>
                <point>19824144/13330577</point>
                <point>19807367/13323777</point>
                <point>19801775/13321509</point>
                <point>19798046/13315836</point>
                <point>19789658/13296525</point>
                <point>19787794/13281730</point>
                <point>19796182/13285146</point>
                <point>19804571/13280591</point>
                <point>19812027/13272614</point>
                <point>19820416/13270333</point>
                <point>19826008/13271474</point>
            </polygon>
        </PolygonMap>
        <PolygonMap name="Cyprus 18 18" zoom="18" mapSource="MapQuest" minTileCoordinate="39575552/26540544" maxTileCoordinate="39901951/26679295">
            <polygon>
                <point>39652017/26542948</point>
                <point>39653882/26547508</point>
                <point>39665066/26554347</point>
                <point>39681844/26561183</point>
                <point>39691164/26561183</point>
                <point>39704213/26554347</point>
                <point>39720990/26547508</point>
                <point>39741496/26542948</point>
                <point>39752681/26545228</point>
                <point>39767594/26547508</point>
                <point>39776915/26545228</point>
                <point>39784371/26549788</point>
                <point>39791828/26558904</point>
                <point>39791828/26581675</point>
                <point>39795556/26581675</point>
                <point>39804877/26572570</point>
                <point>39819790/26577123</point>
                <point>39832839/26577123</point>
                <point>39842159/26572570</point>
                <point>39847752/26572570</point>
                <point>39853344/26570293</point>
                <point>39860801/26565738</point>
                <point>39868257/26561183</point>
                <point>39873850/26561183</point>
                <point>39886898/26568016</point>
                <point>39892491/26565738</point>
                <point>39896219/26570293</point>
                <point>39901812/26583951</point>
                <point>39881306/26588501</point>
                <point>39858936/26588501</point>
                <point>39847752/26588501</point>
                <point>39836567/26588501</point>
                <point>39801148/26624863</point>
                <point>39782507/26638481</point>
                <point>39762001/26645286</point>
                <point>39739632/26649821</point>
                <point>39728447/26649821</point>
                <point>39717262/26656622</point>
                <point>39709806/26663421</point>
                <point>39709806/26672482</point>
                <point>39707942/26679274</point>
                <point>39694893/26677010</point>
                <point>39689300/26663421</point>
                <point>39681844/26658889</point>
                <point>39659474/26661155</point>
                <point>39648289/26661155</point>
                <point>39614735/26647554</point>
                <point>39603550/26643018</point>
                <point>39596093/26631673</point>
                <point>39579316/26593050</point>
                <point>39575588/26563461</point>
                <point>39592365/26570293</point>
                <point>39609142/26561183</point>
                <point>39624055/26545228</point>
                <point>39640833/26540667</point>
                <point>39652017/26542948</point>
            </polygon>
        </PolygonMap>
    </Layer>
</atlas>
